r00arango_connector/__init__.py
r00arango_connector/arango_connector.py
r00arango_connector/helpers/__init__.py
r00arango_connector/helpers/constants.py
r00arango_connector/helpers/exceptions.py
r00arango_connector-0.1.2.dist-info/METADATA
r00arango_connector-0.1.2.dist-info/WHEEL
r00arango_connector-0.1.2.dist-info/RECORD
