Metadata-Version: 2.4
Name: r00arango_connector
Version: 0.1.2
Requires-Python: >=3.10
Requires-Dist: python-arango
Requires-Dist: r00secret
